mobilevikings_scraper/__init__.py
mobile_vikings_scraper-1.0.3.dist-info/LICENSE
mobile_vikings_scraper-1.0.3.dist-info/METADATA
mobile_vikings_scraper-1.0.3.dist-info/WHEEL
mobile_vikings_scraper-1.0.3.dist-info/top_level.txt
mobile_vikings_scraper-1.0.3.dist-info/RECORD
