Metadata-Version: 2.1
Name: mobile-vikings-scraper
Version: 1.0.3
Summary: Scraper for Mobile Vikings in Poland
Home-page: https://github.com/TheLastGimbus/mobile-vikings-scraper
Author: TheLastGimbus
Author-email: mateusz.soszynski@tuta.io
License: Apache
Platform: UNKNOWN
Classifier: Programming Language :: Python :: 3
Classifier: License :: OSI Approved :: Apache Software License
Classifier: Development Status :: 5 - Production/Stable
Classifier: Intended Audience :: Developers
Classifier: Intended Audience :: Telecommunications Industry
Classifier: Topic :: Internet :: WWW/HTTP
Requires-Dist: requests
Requires-Dist: beautifulsoup4
